source_shopify/__init__.py
source_shopify/auth.py
source_shopify/config_migrations.py
source_shopify/http_request.py
source_shopify/run.py
source_shopify/schemas/abandoned_checkouts.json
source_shopify/schemas/articles.json
source_shopify/schemas/balance_transactions.json
source_shopify/schemas/blogs.json
source_shopify/schemas/collections.json
source_shopify/schemas/collects.json
source_shopify/schemas/countries.json
source_shopify/schemas/custom_collections.json
source_shopify/schemas/customer_address.json
source_shopify/schemas/customer_journey_summary.json
source_shopify/schemas/customers.json
source_shopify/schemas/discount_codes.json
source_shopify/schemas/disputes.json
source_shopify/schemas/draft_orders.json
source_shopify/schemas/fulfillment_orders.json
source_shopify/schemas/fulfillments.json
source_shopify/schemas/inventory_items.json
source_shopify/schemas/inventory_levels.json
source_shopify/schemas/locations.json
source_shopify/schemas/metafield_articles.json
source_shopify/schemas/metafield_blogs.json
source_shopify/schemas/metafield_collections.json
source_shopify/schemas/metafield_customers.json
source_shopify/schemas/metafield_draft_orders.json
source_shopify/schemas/metafield_locations.json
source_shopify/schemas/metafield_orders.json
source_shopify/schemas/metafield_pages.json
source_shopify/schemas/metafield_product_images.json
source_shopify/schemas/metafield_product_variants.json
source_shopify/schemas/metafield_products.json
source_shopify/schemas/metafield_shops.json
source_shopify/schemas/metafield_smart_collections.json
source_shopify/schemas/order_agreements.json
source_shopify/schemas/order_refunds.json
source_shopify/schemas/order_risks.json
source_shopify/schemas/orders.json
source_shopify/schemas/pages.json
source_shopify/schemas/price_rules.json
source_shopify/schemas/product_images.json
source_shopify/schemas/product_variants.json
source_shopify/schemas/products.json
source_shopify/schemas/profile_location_groups.json
airbyte_source_shopify-3.0.13.dist-info/METADATA
airbyte_source_shopify-3.0.13.dist-info/WHEEL
airbyte_source_shopify-3.0.13.dist-info/entry_points.txt
airbyte_source_shopify-3.0.13.dist-info/RECORD
