Metadata-Version: 2.1
Name: airbyte-source-shopify
Version: 3.0.13
Summary: Source CDK implementation for Shopify.
Home-page: https://airbyte.com
License: ELv2
Author: Airbyte
Author-email: contact@airbyte.io
Requires-Python: >=3.10,<3.12
Classifier: License :: Other/Proprietary License
Classifier: Programming Language :: Python :: 3
Classifier: Programming Language :: Python :: 3.10
Classifier: Programming Language :: Python :: 3.11
Requires-Dist: airbyte-cdk (>=6,<7)
Requires-Dist: graphql-query (>=1,<2)
Requires-Dist: pendulum (>=2.1.2,<3.0.0)
Requires-Dist: sgqlc (==16.3)
Project-URL: Documentation, https://docs.airbyte.com/integrations/sources/shopify
Project-URL: Repository, https://github.com/airbytehq/airbyte
